{
    "file":{
        "key":"file",
        "name":"文件"
    },
    "view":{
        "key":"view",
        "name":"查看"
    },
    "edit":{
        "key":"edit",
        "name":"编辑",
        "sub":{
            "cancelSelect":{
                "key":"cancelSelect",
                "name":"取消选择",
                "action":"canvas.cancelSelect"
            }
        }
    },
    "canvas":{
        "key":"canvas",
        "name":"画布",
        "sub":{
            "clear":{
                "key":"clear",
                "name":"清空画布",
                "action":"canvas.clear"
            }
        }
    },
    "layer":{
        "key":"layer",
        "name":"图层"
    },
    "setting":{
        "key":"setting",
        "name":"设置"
    },
    "about":{
        "key":"about",
        "name":"关于",
        "sub":{
            "help":{
                "key":"help",
                "name":"帮助",
                "action":"showHelpInfo"
            }
        }
    }
}